sphinx_iconify/__init__.py
sphinx_iconify/roles.py
sphinx_iconify-0.3.0.dist-info/licenses/LICENSE
sphinx_iconify-0.3.0.dist-info/METADATA
sphinx_iconify-0.3.0.dist-info/WHEEL
sphinx_iconify-0.3.0.dist-info/top_level.txt
sphinx_iconify-0.3.0.dist-info/RECORD
